cozo_migrate/__init__.py
cozo_migrate/__main__.py
cozo_migrate/api/__init__.py
cozo_migrate/api/apply.py
cozo_migrate/api/create.py
cozo_migrate/api/history.py
cozo_migrate/api/init.py
cozo_migrate/api/status.py
cozo_migrate/cli/__init__.py
cozo_migrate/cli/apply.py
cozo_migrate/cli/create.py
cozo_migrate/cli/history.py
cozo_migrate/cli/init.py
cozo_migrate/cli/main.py
cozo_migrate/cli/show.py
cozo_migrate/cli/status.py
cozo_migrate/cli/version.py
cozo_migrate/context.py
cozo_migrate/files.py
cozo_migrate/modules.py
cozo_migrate/ops.py
cozo_migrate/queries.py
cozo_migrate/schema.py
cozo_migrate/template.py
cozo_migrate/types.py
cozo_migrate/utils/__init__.py
cozo_migrate/utils/client.py
cozo_migrate/utils/console.py
cozo_migrate/utils/datetime.py
cozo_migrate/utils/fn.py
cozo_migrate/utils/rich.py
cozo_migrate-0.2.4.dist-info/LICENSE
cozo_migrate-0.2.4.dist-info/METADATA
cozo_migrate-0.2.4.dist-info/WHEEL
cozo_migrate-0.2.4.dist-info/entry_points.txt
cozo_migrate-0.2.4.dist-info/RECORD
