Metadata-Version: 2.1
Name: cozo-migrate
Version: 0.2.4
Summary: A simple utility for migrations for cozo db
License: MIT
Author: Diwank Singh Tomer
Author-email: diwank.singh@gmail.com
Requires-Python: >=3.10,<4.0
Classifier: License :: OSI Approved :: MIT License
Classifier: Programming Language :: Python :: 3
Classifier: Programming Language :: Python :: 3.10
Classifier: Programming Language :: Python :: 3.11
Classifier: Programming Language :: Python :: 3.12
Requires-Dist: colorama (>=0.4.0,<0.6.0)
Requires-Dist: cozo-embedded (>=0.7.6,<0.8.0)
Requires-Dist: pandas (>=2.0.0,<2.5.0)
Requires-Dist: pycozo (>=0.7.6,<0.8.0)
Requires-Dist: requests (>=2.0.0,<3.0.0)
Requires-Dist: rich (>=13.0.0,<14.0.0)
Requires-Dist: shellingham (>=1.4.0,<2.0.0)
Requires-Dist: typer (>=0.9.0)
